setup.py
tutils/__init__.py
tutils/fs.py
tutils/version.py
tutils.egg-info/PKG-INFO
tutils.egg-info/SOURCES.txt
tutils.egg-info/dependency_links.txt
tutils.egg-info/not-zip-safe
tutils.egg-info/top_level.txt