Metadata-Version: 1.1
Name: tutils
Version: 1.0.0-alpha.1
Summary: Utils
Home-page: https://bitbucket.org/alexandrul/
Author: Eduard-Cristian Stefan
Author-email: alexandrul.ct@gmail.com
License: Copyright (c) 2014, Eduard-Cristian Stefan
